[
  {
    "deployment_id": "18186137227",
    "repo": "Devyani23625/DQR",
    "status": "success",
    "rollback": false,
    "timestamp": ""
  },
  {
    "deployment_id": "18186172657",
    "repo": "Devyani23625/DQR",
    "status": "success",
    "rollback": false,
    "timestamp": ""
  },
  {
    "deployment_id": "18186240271",
    "repo": "Devyani23625/DQR",
    "status": "success",
    "rollback": false,
    "timestamp": ""
  },
  {
    "deployment_id": "18186269853",
    "repo": "Devyani23625/DQR",
    "status": "success",
    "rollback": true,
    "timestamp": ""
  }
]
